gmc/__init__.py
gmc/config.py
gmc/decorator.py
gmc/device.py
gmc/gmc.py
gmc/util.py
gmc/test/__init__.py
gmc/test/test_gmc300.py
gmc-1.0.0.dist-info/LICENSE
gmc-1.0.0.dist-info/METADATA
gmc-1.0.0.dist-info/WHEEL
gmc-1.0.0.dist-info/top_level.txt
gmc-1.0.0.dist-info/RECORD
