Metadata-Version: 2.1
Name: gmc
Version: 1.0.0
Summary: GMC Geiger counter api
Home-page: https://gitlab.com/slippers/gmc
Author: Kirk Erickson
Author-email: ekirk0+gitlab@gmail.com
License: UNKNOWN
Platform: UNKNOWN
Classifier: Programming Language :: Python :: 3
Classifier: License :: OSI Approved :: GNU General Public License v3 (GPLv3)
Classifier: Operating System :: OS Independent
Requires-Dist: pyserial (==3.4)
